{
    "Ar36": {
        "error": 0.0010633481645565004,
        "error_type": "SEM",
        "filter_outliers_dict": {
            "filter_outliers": true,
            "iterations": 1,
            "std_devs": 2
        },
        "fit": "Linear",
        "value": 0.051940869821742675
    },
    "Ar37": {
        "error": 0.01527460665715692,
        "error_type": "SEM",
        "filter_outliers_dict": {
            "filter_outliers": true,
            "iterations": 1,
            "std_devs": 2
        },
        "fit": "linear",
        "value": 0.03875551654513269
    },
    "Ar38": {
        "error": 0.012575648622592984,
        "error_type": "SEM",
        "filter_outliers_dict": {
            "filter_outliers": true,
            "iterations": 1,
            "std_devs": 2
        },
        "fit": "linear",
        "value": 0.4502902362406307
    },
    "Ar39": {
        "error": 0.03074109951282335,
        "error_type": "SEM",
        "filter_outliers_dict": {
            "filter_outliers": true,
            "iterations": 1,
            "std_devs": 2
        },
        "fit": "Linear",
        "value": 28.018383611611704
    },
    "Ar40": {
        "error": 0.09070756158349376,
        "error_type": "SEM",
        "filter_outliers_dict": {
            "filter_outliers": true,
            "iterations": 1,
            "std_devs": 2
        },
        "fit": "Linear",
        "value": 768.6364249683147
    },
    "Ar41": {
        "error": 0.004770269966598663,
        "error_type": "SEM",
        "filter_outliers_dict": {
            "filter_outliers": true,
            "iterations": 1,
            "std_devs": 2
        },
        "fit": "Average",
        "value": 0.0635735746246133
    }
}